tsp_cw/__init__.py
tsp_cw/tsp_cw.py
tsp_cw-1.1.3.dist-info/METADATA
tsp_cw-1.1.3.dist-info/WHEEL
tsp_cw-1.1.3.dist-info/licenses/LICENSE
tsp_cw-1.1.3.dist-info/RECORD
